<?xml version = '1.0' encoding = 'utf-8' ?>
<?xml-stylesheet type="text/xsl" href="lexicon-transform.xslt"?>
<smor>
<PrefStem>
<Upper>a</Upper>
<Lower>a</Lower>
<Pos>V</Pos>
<Origin>klassisch</Origin>
</PrefStem>
<PrefStem>
<Upper>a</Upper>
<Lower>a</Lower>
<Pos>ADJ</Pos>
<Origin>klassisch</Origin>
</PrefStem>
<PrefStem>
<Upper>a</Upper>
<Lower>a</Lower>
<Pos>NN</Pos>
<Origin>klassisch</Origin>
</PrefStem>
<PrefStem>
<Upper>auto</Upper>
<Lower>auto</Lower>
<Pos>V</Pos>
<Origin>nativ</Origin>
</PrefStem>
<PrefStem>
<Upper>aneinander</Upper>
<Lower>aneinander</Lower>
<Pos>V</Pos>
<Origin>nativ</Origin>
</PrefStem>
<PrefStem>
<Upper>aufeinander</Upper>
<Lower>aufeinander</Lower>
<Pos>V</Pos>
<Origin>nativ</Origin>
</PrefStem>
<PrefStem>
<Upper>anheim</Upper>
<Lower>anheim</Lower>
<Pos>V</Pos>
<Origin>nativ</Origin>
</PrefStem>
<PrefStem>
<Upper>auseinander</Upper>
<Lower>auseinander</Lower>
<Pos>V</Pos>
<Origin>nativ</Origin>
</PrefStem>
<PrefStem>
<Upper>ab</Upper>
<Lower>ab</Lower>
<Pos>V</Pos>
<Origin>nativ</Origin>
</PrefStem>
<PrefStem>
<Upper>an</Upper>
<Lower>an</Lower>
<Pos>V</Pos>
<Origin>nativ</Origin>
</PrefStem>
<PrefStem>
<Upper>auf</Upper>
<Lower>auf</Lower>
<Pos>V</Pos>
<Origin>nativ</Origin>
</PrefStem>
<PrefStem>
<Upper>aus</Upper>
<Lower>aus</Lower>
<Pos>V</Pos>
<Origin>nativ</Origin>
</PrefStem>
<PrefStem>
<Upper>be</Upper>
<Lower>be</Lower>
<Pos>V</Pos>
<Origin>nativ</Origin>
</PrefStem>
<PrefStem>
<Upper>bei</Upper>
<Lower>bei</Lower>
<Pos>V</Pos>
<Origin>nativ</Origin>
</PrefStem>
<PrefStem>
<Upper>beisammen</Upper>
<Lower>beisammen</Lower>
<Pos>V</Pos>
<Origin>nativ</Origin>
</PrefStem>
<PrefStem>
<Upper>bekannt</Upper>
<Lower>bekannt</Lower>
<Pos>V</Pos>
<Origin>nativ</Origin>
</PrefStem>
<PrefStem>
<Upper>bereit</Upper>
<Lower>bereit</Lower>
<Pos>V</Pos>
<Origin>nativ</Origin>
</PrefStem>
<PrefStem>
<Upper>bevor</Upper>
<Lower>bevor</Lower>
<Pos>V</Pos>
<Origin>nativ</Origin>
</PrefStem>
<PrefStem>
<Upper>brach</Upper>
<Lower>brach</Lower>
<Pos>V</Pos>
<Origin>nativ</Origin>
</PrefStem>
<PrefStem>
<Upper>bau</Upper>
<Lower>bau</Lower>
<Pos>V</Pos>
<Origin>nativ</Origin>
</PrefStem>
<PrefStem>
<Upper>bloß</Upper>
<Lower>bloß</Lower>
<Pos>V</Pos>
<Origin>nativ</Origin>
</PrefStem>
<PrefStem>
<Upper>breit</Upper>
<Lower>breit</Lower>
<Pos>V</Pos>
<Origin>nativ</Origin>
</PrefStem>
<PrefStem>
<Upper>da</Upper>
<Lower>da</Lower>
<Pos>V</Pos>
<Origin>nativ</Origin>
</PrefStem>
<PrefStem>
<Upper>dabei</Upper>
<Lower>dabei</Lower>
<Pos>V</Pos>
<Origin>nativ</Origin>
</PrefStem>
<PrefStem>
<Upper>daher</Upper>
<Lower>daher</Lower>
<Pos>V</Pos>
<Origin>nativ</Origin>
</PrefStem>
<PrefStem>
<Upper>dahin</Upper>
<Lower>dahin</Lower>
<Pos>V</Pos>
<Origin>nativ</Origin>
</PrefStem>
<PrefStem>
<Upper>daneben</Upper>
<Lower>daneben</Lower>
<Pos>V</Pos>
<Origin>nativ</Origin>
</PrefStem>
<PrefStem>
<Upper>daran</Upper>
<Lower>daran</Lower>
<Pos>V</Pos>
<Origin>nativ</Origin>
</PrefStem>
<PrefStem>
<Upper>dar</Upper>
<Lower>dar</Lower>
<Pos>V</Pos>
<Origin>nativ</Origin>
</PrefStem>
<PrefStem>
<Upper>davon</Upper>
<Lower>davon</Lower>
<Pos>V</Pos>
<Origin>nativ</Origin>
</PrefStem>
<PrefStem>
<Upper>dazu</Upper>
<Lower>dazu</Lower>
<Pos>V</Pos>
<Origin>nativ</Origin>
</PrefStem>
<PrefStem>
<Upper>dicht</Upper>
<Lower>dicht</Lower>
<Pos>V</Pos>
<Origin>nativ</Origin>
</PrefStem>
<PrefStem>
<Upper>dran</Upper>
<Lower>dran</Lower>
<Pos>V</Pos>
<Origin>nativ</Origin>
</PrefStem>
<PrefStem>
<Upper>drein</Upper>
<Lower>drein</Lower>
<Pos>V</Pos>
<Origin>nativ</Origin>
</PrefStem>
<PrefStem>
<Upper>durch</Upper>
<Lower>durch</Lower>
<Pos>V</Pos>
<Origin>nativ</Origin>
</PrefStem>
<PrefStem>
<Upper>durcheinander</Upper>
<Lower>durcheinander</Lower>
<Pos>V</Pos>
<Origin>nativ</Origin>
</PrefStem>
<PrefStem>
<Upper>durch</Upper>
<Lower>durch</Lower>
<Pos>V</Pos>
<Origin>nativ</Origin>
</PrefStem>
<PrefStem>
<Upper>empor</Upper>
<Lower>empor</Lower>
<Pos>V</Pos>
<Origin>nativ</Origin>
</PrefStem>
<PrefStem>
<Upper>ein</Upper>
<Lower>ein</Lower>
<Pos>V</Pos>
<Origin>nativ</Origin>
</PrefStem>
<PrefStem>
<Upper>einher</Upper>
<Lower>einher</Lower>
<Pos>V</Pos>
<Origin>nativ</Origin>
</PrefStem>
<PrefStem>
<Upper>energie</Upper>
<Lower>energie</Lower>
<Pos>V</Pos>
<Origin>nativ</Origin>
</PrefStem>
<PrefStem>
<Upper>entgegen</Upper>
<Lower>entgegen</Lower>
<Pos>V</Pos>
<Origin>nativ</Origin>
</PrefStem>
<PrefStem>
<Upper>ent</Upper>
<Lower>ent</Lower>
<Pos>V</Pos>
<Origin>nativ</Origin>
</PrefStem>
<PrefStem>
<Upper>ernst</Upper>
<Lower>ernst</Lower>
<Pos>V</Pos>
<Origin>nativ</Origin>
</PrefStem>
<PrefStem>
<Upper>fach</Upper>
<Lower>fach</Lower>
<Pos>V</Pos>
<Origin>nativ</Origin>
</PrefStem>
<PrefStem>
<Upper>fallen</Upper>
<Lower>fallen</Lower>
<Pos>V</Pos>
<Origin>nativ</Origin>
</PrefStem>
<PrefStem>
<Upper>fehl</Upper>
<Lower>fehl</Lower>
<Pos>V</Pos>
<Origin>nativ</Origin>
</PrefStem>
<PrefStem>
<Upper>feil</Upper>
<Lower>feil</Lower>
<Pos>V</Pos>
<Origin>nativ</Origin>
</PrefStem>
<PrefStem>
<Upper>fern</Upper>
<Lower>fern</Lower>
<Pos>V</Pos>
<Origin>nativ</Origin>
</PrefStem>
<PrefStem>
<Upper>fertig</Upper>
<Lower>fertig</Lower>
<Pos>V</Pos>
<Origin>nativ</Origin>
</PrefStem>
<PrefStem>
<Upper>fest</Upper>
<Lower>fest</Lower>
<Pos>V</Pos>
<Origin>nativ</Origin>
</PrefStem>
<PrefStem>
<Upper>fort</Upper>
<Lower>fort</Lower>
<Pos>V</Pos>
<Origin>nativ</Origin>
</PrefStem>
<PrefStem>
<Upper>frei</Upper>
<Lower>frei</Lower>
<Pos>V</Pos>
<Origin>nativ</Origin>
</PrefStem>
<PrefStem>
<Upper>frisch</Upper>
<Lower>frisch</Lower>
<Pos>V</Pos>
<Origin>nativ</Origin>
</PrefStem>
<PrefStem>
<Upper>geheim</Upper>
<Lower>geheim</Lower>
<Pos>V</Pos>
<Origin>nativ</Origin>
</PrefStem>
<PrefStem>
<Upper>gegen</Upper>
<Lower>gegen</Lower>
<Pos>V</Pos>
<Origin>nativ</Origin>
</PrefStem>
<PrefStem>
<Upper>gegenüber</Upper>
<Lower>gegenüber</Lower>
<Pos>V</Pos>
<Origin>nativ</Origin>
</PrefStem>
<PrefStem>
<Upper>gerade</Upper>
<Lower>gerade</Lower>
<Pos>V</Pos>
<Origin>nativ</Origin>
</PrefStem>
<PrefStem>
<Upper>gleich</Upper>
<Lower>gleich</Lower>
<Pos>V</Pos>
<Origin>nativ</Origin>
</PrefStem>
<PrefStem>
<Upper>groß</Upper>
<Lower>groß</Lower>
<Pos>V</Pos>
<Origin>nativ</Origin>
</PrefStem>
<PrefStem>
<Upper>gut</Upper>
<Lower>gut</Lower>
<Pos>V</Pos>
<Origin>nativ</Origin>
</PrefStem>
<PrefStem>
<Upper>hand</Upper>
<Lower>hand</Lower>
<Pos>V</Pos>
<Origin>nativ</Origin>
</PrefStem>
<PrefStem>
<Upper>halt</Upper>
<Lower>halt</Lower>
<Pos>V</Pos>
<Origin>nativ</Origin>
</PrefStem>
<PrefStem>
<Upper>hängen</Upper>
<Lower>hängen</Lower>
<Pos>V</Pos>
<Origin>nativ</Origin>
</PrefStem>
<PrefStem>
<Upper>heim</Upper>
<Lower>heim</Lower>
<Pos>V</Pos>
<Origin>nativ</Origin>
</PrefStem>
<PrefStem>
<Upper>her</Upper>
<Lower>her</Lower>
<Pos>V</Pos>
<Origin>nativ</Origin>
</PrefStem>
<PrefStem>
<Upper>heran</Upper>
<Lower>heran</Lower>
<Pos>V</Pos>
<Origin>nativ</Origin>
</PrefStem>
<PrefStem>
<Upper>herab</Upper>
<Lower>herab</Lower>
<Pos>V</Pos>
<Origin>nativ</Origin>
</PrefStem>
<PrefStem>
<Upper>herauf</Upper>
<Lower>herauf</Lower>
<Pos>V</Pos>
<Origin>nativ</Origin>
</PrefStem>
<PrefStem>
<Upper>heraus</Upper>
<Lower>heraus</Lower>
<Pos>V</Pos>
<Origin>nativ</Origin>
</PrefStem>
<PrefStem>
<Upper>herbei</Upper>
<Lower>herbei</Lower>
<Pos>V</Pos>
<Origin>nativ</Origin>
</PrefStem>
<PrefStem>
<Upper>herein</Upper>
<Lower>herein</Lower>
<Pos>V</Pos>
<Origin>nativ</Origin>
</PrefStem>
<PrefStem>
<Upper>herum</Upper>
<Lower>herum</Lower>
<Pos>V</Pos>
<Origin>nativ</Origin>
</PrefStem>
<PrefStem>
<Upper>herunter</Upper>
<Lower>herunter</Lower>
<Pos>V</Pos>
<Origin>nativ</Origin>
</PrefStem>
<PrefStem>
<Upper>hervor</Upper>
<Lower>hervor</Lower>
<Pos>V</Pos>
<Origin>nativ</Origin>
</PrefStem>
<PrefStem>
<Upper>herüber</Upper>
<Lower>herüber</Lower>
<Pos>V</Pos>
<Origin>nativ</Origin>
</PrefStem>
<PrefStem>
<Upper>hierher</Upper>
<Lower>hierher</Lower>
<Pos>V</Pos>
<Origin>nativ</Origin>
</PrefStem>
<PrefStem>
<Upper>hin</Upper>
<Lower>hin</Lower>
<Pos>V</Pos>
<Origin>nativ</Origin>
</PrefStem>
<PrefStem>
<Upper>hinab</Upper>
<Lower>hinab</Lower>
<Pos>V</Pos>
<Origin>nativ</Origin>
</PrefStem>
<PrefStem>
<Upper>hinauf</Upper>
<Lower>hinauf</Lower>
<Pos>V</Pos>
<Origin>nativ</Origin>
</PrefStem>
<PrefStem>
<Upper>hinaus</Upper>
<Lower>hinaus</Lower>
<Pos>V</Pos>
<Origin>nativ</Origin>
</PrefStem>
<PrefStem>
<Upper>hinein</Upper>
<Lower>hinein</Lower>
<Pos>V</Pos>
<Origin>nativ</Origin>
</PrefStem>
<PrefStem>
<Upper>hinter</Upper>
<Lower>hinter</Lower>
<Pos>V</Pos>
<Origin>nativ</Origin>
</PrefStem>
<PrefStem>
<Upper>hinterher</Upper>
<Lower>hinterher</Lower>
<Pos>V</Pos>
<Origin>nativ</Origin>
</PrefStem>
<PrefStem>
<Upper>hinunter</Upper>
<Lower>hinunter</Lower>
<Pos>V</Pos>
<Origin>nativ</Origin>
</PrefStem>
<PrefStem>
<Upper>hinweg</Upper>
<Lower>hinweg</Lower>
<Pos>V</Pos>
<Origin>nativ</Origin>
</PrefStem>
<PrefStem>
<Upper>hinzu</Upper>
<Lower>hinzu</Lower>
<Pos>V</Pos>
<Origin>nativ</Origin>
</PrefStem>
<PrefStem>
<Upper>hinüber</Upper>
<Lower>hinüber</Lower>
<Pos>V</Pos>
<Origin>nativ</Origin>
</PrefStem>
<PrefStem>
<Upper>hoch</Upper>
<Lower>hoch</Lower>
<Pos>V</Pos>
<Origin>nativ</Origin>
</PrefStem>
<PrefStem>
<Upper>ineinander</Upper>
<Lower>ineinander</Lower>
<Pos>V</Pos>
<Origin>nativ</Origin>
</PrefStem>
<PrefStem>
<Upper>inne</Upper>
<Lower>inne</Lower>
<Pos>V</Pos>
<Origin>nativ</Origin>
</PrefStem>
<PrefStem>
<Upper>kaputt</Upper>
<Lower>kaputt</Lower>
<Pos>V</Pos>
<Origin>nativ</Origin>
</PrefStem>
<PrefStem>
<Upper>kennen</Upper>
<Lower>kennen</Lower>
<Pos>V</Pos>
<Origin>nativ</Origin>
</PrefStem>
<PrefStem>
<Upper>klar</Upper>
<Lower>klar</Lower>
<Pos>V</Pos>
<Origin>nativ</Origin>
</PrefStem>
<PrefStem>
<Upper>klein</Upper>
<Lower>klein</Lower>
<Pos>V</Pos>
<Origin>nativ</Origin>
</PrefStem>
<PrefStem>
<Upper>kopf</Upper>
<Lower>kopf</Lower>
<Pos>V</Pos>
<Origin>nativ</Origin>
</PrefStem>
<PrefStem>
<Upper>krank</Upper>
<Lower>krank</Lower>
<Pos>V</Pos>
<Origin>nativ</Origin>
</PrefStem>
<PrefStem>
<Upper>kund</Upper>
<Lower>kund</Lower>
<Pos>V</Pos>
<Origin>nativ</Origin>
</PrefStem>
<PrefStem>
<Upper>lahm</Upper>
<Lower>lahm</Lower>
<Pos>V</Pos>
<Origin>nativ</Origin>
</PrefStem>
<PrefStem>
<Upper>lieb</Upper>
<Lower>lieb</Lower>
<Pos>V</Pos>
<Origin>nativ</Origin>
</PrefStem>
<PrefStem>
<Upper>liegen</Upper>
<Lower>liegen</Lower>
<Pos>V</Pos>
<Origin>nativ</Origin>
</PrefStem>
<PrefStem>
<Upper>los</Upper>
<Lower>los</Lower>
<Pos>V</Pos>
<Origin>nativ</Origin>
</PrefStem>
<PrefStem>
<Upper>maß</Upper>
<Lower>maß</Lower>
<Pos>V</Pos>
<Origin>nativ</Origin>
</PrefStem>
<PrefStem>
<Upper>miss</Upper>
<Lower>miss</Lower>
<Pos>V</Pos>
<Origin>nativ</Origin>
</PrefStem>
<PrefStem>
<Upper>mit</Upper>
<Lower>mit</Lower>
<Pos>V</Pos>
<Origin>nativ</Origin>
</PrefStem>
<PrefStem>
<Upper>mitan</Upper>
<Lower>mitan</Lower>
<Pos>V</Pos>
<Origin>nativ</Origin>
</PrefStem>
<PrefStem>
<Upper>mitein</Upper>
<Lower>mitein</Lower>
<Pos>V</Pos>
<Origin>nativ</Origin>
</PrefStem>
<PrefStem>
<Upper>mut</Upper>
<Lower>mut</Lower>
<Pos>V</Pos>
<Origin>nativ</Origin>
</PrefStem>
<PrefStem>
<Upper>nach</Upper>
<Lower>nach</Lower>
<Pos>V</Pos>
<Origin>nativ</Origin>
</PrefStem>
<PrefStem>
<Upper>nebeneinander</Upper>
<Lower>nebeneinander</Lower>
<Pos>V</Pos>
<Origin>nativ</Origin>
</PrefStem>
<PrefStem>
<Upper>nieder</Upper>
<Lower>nieder</Lower>
<Pos>V</Pos>
<Origin>nativ</Origin>
</PrefStem>
<PrefStem>
<Upper>näher</Upper>
<Lower>näher</Lower>
<Pos>V</Pos>
<Origin>nativ</Origin>
</PrefStem>
<PrefStem>
<Upper>nahe</Upper>
<Lower>nahe</Lower>
<Pos>V</Pos>
<Origin>nativ</Origin>
</PrefStem>
<PrefStem>
<Upper>neu</Upper>
<Lower>neu</Lower>
<Pos>V</Pos>
<Origin>nativ</Origin>
</PrefStem>
<PrefStem>
<Upper>not</Upper>
<Lower>not</Lower>
<Pos>V</Pos>
<Origin>nativ</Origin>
</PrefStem>
<PrefStem>
<Upper>offen</Upper>
<Lower>offen</Lower>
<Pos>V</Pos>
<Origin>nativ</Origin>
</PrefStem>
<PrefStem>
<Upper>preis</Upper>
<Lower>preis</Lower>
<Pos>V</Pos>
<Origin>nativ</Origin>
</PrefStem>
<PrefStem>
<Upper>rad</Upper>
<Lower>rad</Lower>
<Pos>V</Pos>
<Origin>nativ</Origin>
</PrefStem>
<PrefStem>
<Upper>raus</Upper>
<Lower>raus</Lower>
<Pos>V</Pos>
<Origin>nativ</Origin>
</PrefStem>
<PrefStem>
<Upper>rein</Upper>
<Lower>rein</Lower>
<Pos>V</Pos>
<Origin>nativ</Origin>
</PrefStem>
<PrefStem>
<Upper>rüber</Upper>
<Lower>rüber</Lower>
<Pos>V</Pos>
<Origin>nativ</Origin>
</PrefStem>
<PrefStem>
<Upper>rück</Upper>
<Lower>rück</Lower>
<Pos>V</Pos>
<Origin>nativ</Origin>
</PrefStem>
<PrefStem>
<Upper>runter</Upper>
<Lower>runter</Lower>
<Pos>V</Pos>
<Origin>nativ</Origin>
</PrefStem>
<PrefStem>
<Upper>schief</Upper>
<Lower>schief</Lower>
<Pos>V</Pos>
<Origin>nativ</Origin>
</PrefStem>
<PrefStem>
<Upper>schön</Upper>
<Lower>schön</Lower>
<Pos>V</Pos>
<Origin>nativ</Origin>
</PrefStem>
<PrefStem>
<Upper>schwer</Upper>
<Lower>schwer</Lower>
<Pos>V</Pos>
<Origin>nativ</Origin>
</PrefStem>
<PrefStem>
<Upper>sicher</Upper>
<Lower>sicher</Lower>
<Pos>V</Pos>
<Origin>nativ</Origin>
</PrefStem>
<PrefStem>
<Upper>sitzen</Upper>
<Lower>sitzen</Lower>
<Pos>V</Pos>
<Origin>nativ</Origin>
</PrefStem>
<PrefStem>
<Upper>ski</Upper>
<Lower>ski</Lower>
<Pos>V</Pos>
<Origin>nativ</Origin>
</PrefStem>
<PrefStem>
<Upper>spazieren</Upper>
<Lower>spazieren</Lower>
<Pos>V</Pos>
<Origin>nativ</Origin>
</PrefStem>
<PrefStem>
<Upper>stand</Upper>
<Lower>stand</Lower>
<Pos>V</Pos>
<Origin>nativ</Origin>
</PrefStem>
<PrefStem>
<Upper>statt</Upper>
<Lower>statt</Lower>
<Pos>V</Pos>
<Origin>nativ</Origin>
</PrefStem>
<PrefStem>
<Upper>stecken</Upper>
<Lower>stecken</Lower>
<Pos>V</Pos>
<Origin>nativ</Origin>
</PrefStem>
<PrefStem>
<Upper>stehen</Upper>
<Lower>stehen</Lower>
<Pos>V</Pos>
<Origin>nativ</Origin>
</PrefStem>
<PrefStem>
<Upper>still</Upper>
<Lower>still</Lower>
<Pos>V</Pos>
<Origin>nativ</Origin>
</PrefStem>
<PrefStem>
<Upper>teil</Upper>
<Lower>teil</Lower>
<Pos>V</Pos>
<Origin>nativ</Origin>
</PrefStem>
<PrefStem>
<Upper>tot</Upper>
<Lower>tot</Lower>
<Pos>V</Pos>
<Origin>nativ</Origin>
</PrefStem>
<PrefStem>
<Upper>trans</Upper>
<Lower>trans</Lower>
<Pos>V</Pos>
<Origin>nativ</Origin>
</PrefStem>
<PrefStem>
<Upper>übel</Upper>
<Lower>übel</Lower>
<Pos>V</Pos>
<Origin>nativ</Origin>
</PrefStem>
<PrefStem>
<Upper>über</Upper>
<Lower>über</Lower>
<Pos>V</Pos>
<Origin>nativ</Origin>
</PrefStem>
<PrefStem>
<Upper>überein</Upper>
<Lower>überein</Lower>
<Pos>V</Pos>
<Origin>nativ</Origin>
</PrefStem>
<PrefStem>
<Upper>überhand</Upper>
<Lower>überhand</Lower>
<Pos>V</Pos>
<Origin>nativ</Origin>
</PrefStem>
<PrefStem>
<Upper>übrig</Upper>
<Lower>übrig</Lower>
<Pos>V</Pos>
<Origin>nativ</Origin>
</PrefStem>
<PrefStem>
<Upper>um</Upper>
<Lower>um</Lower>
<Pos>V</Pos>
<Origin>nativ</Origin>
</PrefStem>
<PrefStem>
<Upper>umher</Upper>
<Lower>umher</Lower>
<Pos>V</Pos>
<Origin>nativ</Origin>
</PrefStem>
<PrefStem>
<Upper>umhin</Upper>
<Lower>umhin</Lower>
<Pos>V</Pos>
<Origin>nativ</Origin>
</PrefStem>
<PrefStem>
<Upper>un</Upper>
<Lower>un</Lower>
<Pos>ADJ</Pos>
<Origin>nativ</Origin>
</PrefStem>
<PrefStem>
<Upper>unter</Upper>
<Lower>unter</Lower>
<Pos>V</Pos>
<Origin>nativ</Origin>
</PrefStem>
<PrefStem>
<Upper>urauf</Upper>
<Lower>urauf</Lower>
<Pos>V</Pos>
<Origin>nativ</Origin>
</PrefStem>
<PrefStem>
<Upper>ver</Upper>
<Lower>ver</Lower>
<Pos>V</Pos>
<Origin>nativ</Origin>
</PrefStem>
<PrefStem>
<Upper>verloren</Upper>
<Lower>verloren</Lower>
<Pos>V</Pos>
<Origin>nativ</Origin>
</PrefStem>
<PrefStem>
<Upper>voll</Upper>
<Lower>voll</Lower>
<Pos>V</Pos>
<Origin>nativ</Origin>
</PrefStem>
<PrefStem>
<Upper>vor</Upper>
<Lower>vor</Lower>
<Pos>V</Pos>
<Origin>nativ</Origin>
</PrefStem>
<PrefStem>
<Upper>voran</Upper>
<Lower>voran</Lower>
<Pos>V</Pos>
<Origin>nativ</Origin>
</PrefStem>
<PrefStem>
<Upper>voraus</Upper>
<Lower>voraus</Lower>
<Pos>V</Pos>
<Origin>nativ</Origin>
</PrefStem>
<PrefStem>
<Upper>vorbei</Upper>
<Lower>vorbei</Lower>
<Pos>V</Pos>
<Origin>nativ</Origin>
</PrefStem>
<PrefStem>
<Upper>vorher</Upper>
<Lower>vorher</Lower>
<Pos>V</Pos>
<Origin>nativ</Origin>
</PrefStem>
<PrefStem>
<Upper>vorwärts</Upper>
<Lower>vorwärts</Lower>
<Pos>V</Pos>
<Origin>nativ</Origin>
</PrefStem>
<PrefStem>
<Upper>vorweg</Upper>
<Lower>vorweg</Lower>
<Pos>V</Pos>
<Origin>nativ</Origin>
</PrefStem>
<PrefStem>
<Upper>wach</Upper>
<Lower>wach</Lower>
<Pos>V</Pos>
<Origin>nativ</Origin>
</PrefStem>
<PrefStem>
<Upper>wahr</Upper>
<Lower>wahr</Lower>
<Pos>V</Pos>
<Origin>nativ</Origin>
</PrefStem>
<PrefStem>
<Upper>weg</Upper>
<Lower>weg</Lower>
<Pos>V</Pos>
<Origin>nativ</Origin>
</PrefStem>
<PrefStem>
<Upper>weis</Upper>
<Lower>weis</Lower>
<Pos>V</Pos>
<Origin>nativ</Origin>
</PrefStem>
<PrefStem>
<Upper>weiter</Upper>
<Lower>weiter</Lower>
<Pos>V</Pos>
<Origin>nativ</Origin>
</PrefStem>
<PrefStem>
<Upper>wett</Upper>
<Lower>wett</Lower>
<Pos>V</Pos>
<Origin>nativ</Origin>
</PrefStem>
<PrefStem>
<Upper>wider</Upper>
<Lower>wider</Lower>
<Pos>V</Pos>
<Origin>nativ</Origin>
</PrefStem>
<PrefStem>
<Upper>wieder</Upper>
<Lower>wieder</Lower>
<Pos>V</Pos>
<Origin>nativ</Origin>
</PrefStem>
<PrefStem>
<Upper>wiederan</Upper>
<Lower>wiederan</Lower>
<Pos>V</Pos>
<Origin>nativ</Origin>
</PrefStem>
<PrefStem>
<Upper>wiederauf</Upper>
<Lower>wiederauf</Lower>
<Pos>V</Pos>
<Origin>nativ</Origin>
</PrefStem>
<PrefStem>
<Upper>wiederein</Upper>
<Lower>wiederein</Lower>
<Pos>V</Pos>
<Origin>nativ</Origin>
</PrefStem>
<PrefStem>
<Upper>wiedergut</Upper>
<Lower>wiedergut</Lower>
<Pos>V</Pos>
<Origin>nativ</Origin>
</PrefStem>
<PrefStem>
<Upper>wiederher</Upper>
<Lower>wiederher</Lower>
<Pos>V</Pos>
<Origin>nativ</Origin>
</PrefStem>
<PrefStem>
<Upper>wohl</Upper>
<Lower>wohl</Lower>
<Pos>V</Pos>
<Origin>nativ</Origin>
</PrefStem>
<PrefStem>
<Upper>zer</Upper>
<Lower>zer</Lower>
<Pos>V</Pos>
<Origin>nativ</Origin>
</PrefStem>
<PrefStem>
<Upper>zu</Upper>
<Lower>zu</Lower>
<Pos>V</Pos>
<Origin>nativ</Origin>
</PrefStem>
<PrefStem>
<Upper>zurecht</Upper>
<Lower>zurecht</Lower>
<Pos>V</Pos>
<Origin>nativ</Origin>
</PrefStem>
<PrefStem>
<Upper>zurück</Upper>
<Lower>zurück</Lower>
<Pos>V</Pos>
<Origin>nativ</Origin>
</PrefStem>
<PrefStem>
<Upper>zusammen</Upper>
<Lower>zusammen</Lower>
<Pos>V</Pos>
<Origin>nativ</Origin>
</PrefStem>
<PrefStem>
<Upper>zufrieden</Upper>
<Lower>zufrieden</Lower>
<Pos>V</Pos>
<Origin>nativ</Origin>
</PrefStem>
<PrefStem>
<Upper>zugrunde</Upper>
<Lower>zugrunde</Lower>
<Pos>V</Pos>
<Origin>nativ</Origin>
</PrefStem>
<PrefStem>
<Upper>zugute</Upper>
<Lower>zugute</Lower>
<Pos>V</Pos>
<Origin>nativ</Origin>
</PrefStem>
<PrefStem>
<Upper>zurück</Upper>
<Lower>zurück</Lower>
<Pos>V</Pos>
<Origin>nativ</Origin>
</PrefStem>
<PrefStem>
<Upper>zusammen</Upper>
<Lower>zusammen</Lower>
<Pos>V</Pos>
<Origin>nativ</Origin>
</PrefStem>
<PrefStem>
<Upper>zustande</Upper>
<Lower>zustande</Lower>
<Pos>V</Pos>
<Origin>nativ</Origin>
</PrefStem>
<PrefStem>
<Upper>zuvor</Upper>
<Lower>zuvor</Lower>
<Pos>V</Pos>
<Origin>nativ</Origin>
</PrefStem>
<PrefStem>
<Upper>zuwider</Upper>
<Lower>zuwider</Lower>
<Pos>V</Pos>
<Origin>nativ</Origin>
</PrefStem>
<PrefStem>
<Upper>zu</Upper>
<Lower>zu</Lower>
<Pos>V</Pos>
<Origin>nativ</Origin>
</PrefStem>
<PrefStem>
<Upper>re</Upper>
<Lower>re</Lower>
<Pos>NN</Pos>
<Origin>klassisch</Origin>
</PrefStem>
<PrefStem>
<Upper>i</Upper>
<Lower>i</Lower>
<Pos>NN</Pos>
<Origin>klassisch</Origin>
</PrefStem>
<PrefStem>
<Upper>i</Upper>
<Lower>i</Lower>
<Pos>NN</Pos>
<Origin>klassisch</Origin>
<Origin>nativ</Origin>
</PrefStem>
<PrefStem>
<Upper>infra</Upper>
<Lower>infra</Lower>
<Pos>V</Pos>
<Origin>klassisch</Origin>
</PrefStem>
<PrefStem>
<Upper>kontra</Upper>
<Lower>kontra</Lower>
<Pos>V</Pos>
<Origin>klassisch</Origin>
<Origin>nativ</Origin>
</PrefStem>
<PrefStem>
<Upper>außer</Upper>
<Lower>außer</Lower>
<Pos>ADJ</Pos>
<Origin>nativ</Origin>
</PrefStem>
<PrefStem>
<Upper>dis</Upper>
<Lower>dis</Lower>
<Pos>ADJ</Pos>
<Origin>fremd</Origin>
<Origin>klassisch</Origin>
<Origin>nativ</Origin>
</PrefStem>
<PrefStem>
<Upper>extra</Upper>
<Lower>extra</Lower>
<Pos>ADJ</Pos>
<Origin>fremd</Origin>
<Origin>klassisch</Origin>
<Origin>nativ</Origin>
</PrefStem>
<PrefStem>
<Upper>inner</Upper>
<Lower>inner</Lower>
<Pos>ADJ</Pos>
<Origin>fremd</Origin>
<Origin>klassisch</Origin>
<Origin>nativ</Origin>
</PrefStem>
<PrefStem>
<Upper>mega</Upper>
<Lower>mega</Lower>
<Pos>ADJ</Pos>
<Origin>fremd</Origin>
<Origin>klassisch</Origin>
<Origin>nativ</Origin>
</PrefStem>
<PrefStem>
<Upper>multi</Upper>
<Lower>multi</Lower>
<Pos>NN</Pos>
<Origin>fremd</Origin>
<Origin>klassisch</Origin>
<Origin>nativ</Origin>
</PrefStem>
<PrefStem>
<Upper>neo</Upper>
<Lower>neo</Lower>
<Pos>ADJ</Pos>
<Origin>fremd</Origin>
<Origin>klassisch</Origin>
<Origin>nativ</Origin>
</PrefStem>
<PrefStem>
<Upper>non</Upper>
<Lower>non</Lower>
<Pos>ADJ</Pos>
<Origin>fremd</Origin>
<Origin>klassisch</Origin>
<Origin>nativ</Origin>
</PrefStem>
<PrefStem>
<Upper>para</Upper>
<Lower>para</Lower>
<Pos>ADJ</Pos>
<Origin>klassisch</Origin>
</PrefStem>
<PrefStem>
<Upper>post</Upper>
<Lower>post</Lower>
<Pos>ADJ</Pos>
<Origin>fremd</Origin>
<Origin>klassisch</Origin>
<Origin>nativ</Origin>
</PrefStem>
<PrefStem>
<Upper>retro</Upper>
<Lower>retro</Lower>
<Pos>ADJ</Pos>
<Origin>fremd</Origin>
<Origin>klassisch</Origin>
<Origin>nativ</Origin>
</PrefStem>
<PrefStem>
<Upper>semi</Upper>
<Lower>semi</Lower>
<Pos>ADJ</Pos>
<Origin>fremd</Origin>
<Origin>klassisch</Origin>
<Origin>nativ</Origin>
</PrefStem>
<PrefStem>
<Upper>supra</Upper>
<Lower>supra</Lower>
<Pos>ADJ</Pos>
<Origin>klassisch</Origin>
<Origin>nativ</Origin>
</PrefStem>
<PrefStem>
<Upper>pan</Upper>
<Lower>pan</Lower>
<Pos>NE</Pos>
<Origin>fremd</Origin>
</PrefStem>
<PrefStem>
<Upper>meta</Upper>
<Lower>meta</Lower>
<Pos>NN</Pos>
<Origin>klassisch</Origin>
<Origin>nativ</Origin>
</PrefStem>
<PrefStem>
<Upper>mega</Upper>
<Lower>mega</Lower>
<Pos>NN</Pos>
<Origin>fremd</Origin>
<Origin>klassisch</Origin>
<Origin>nativ</Origin>
</PrefStem>
<PrefStem>
<Upper>micro</Upper>
<Lower>micro</Lower>
<Pos>NN</Pos>
<Origin>fremd</Origin>
<Origin>klassisch</Origin>
<Origin>nativ</Origin>
</PrefStem>
<PrefStem>
<Upper>para</Upper>
<Lower>para</Lower>
<Pos>NN</Pos>
<Origin>klassisch</Origin>
</PrefStem>
<PrefStem>
<Upper>post</Upper>
<Lower>post</Lower>
<Pos>NN</Pos>
<Origin>fremd</Origin>
<Origin>klassisch</Origin>
<Origin>nativ</Origin>
</PrefStem>
<PrefStem>
<Upper>retro</Upper>
<Lower>retro</Lower>
<Pos>NN</Pos>
<Origin>nativ</Origin>
<Origin>fremd</Origin>
</PrefStem>
<PrefStem>
<Upper>semi</Upper>
<Lower>semi</Lower>
<Pos>NN</Pos>
<Origin>nativ</Origin>
</PrefStem>
<PrefStem>
<Upper>stief</Upper>
<Lower>stief</Lower>
<Pos>NN</Pos>
<Origin>nativ</Origin>
</PrefStem>
<PrefStem>
<Upper>über</Upper>
<Lower>über</Lower>
<Pos>V</Pos>
<Origin>nativ</Origin>
</PrefStem>
<PrefStem>
<Upper>re</Upper>
<Lower>re</Lower>
<Pos>ADJ</Pos>
<Pos>NN</Pos>
<Pos>V</Pos>
<Origin>klassisch</Origin>
</PrefStem>
</smor>
